fdir.py
fdir_cli-2.0.0.dist-info/licenses/LICENSE.md
fdir_cli-2.0.0.dist-info/METADATA
fdir_cli-2.0.0.dist-info/WHEEL
fdir_cli-2.0.0.dist-info/entry_points.txt
fdir_cli-2.0.0.dist-info/top_level.txt
fdir_cli-2.0.0.dist-info/RECORD
