Metadata-Version: 2.4
Name: fdir-cli
Version: 2.0.0
Summary: Command-line utility to list, filter, and sort files in a directory
Requires-Python: >=3.8
License-File: LICENSE.md
Dynamic: license-file
Dynamic: requires-python
Dynamic: summary
